agents/__init__.py
agents/graph.py
agents/nodes.py
agents/state.py
agents/tool.py
config/__init__.py
config/settings.py
database/__init__.py
database/models.py
database/storage.py
llms/__init__.py
llms/factory.py
llms/providers.py
run/__init__.py
run/main.py
tools/__init__.py
tools/babu_bhaiya_node_tools.py
tools/raju_node_tools.py
tools/shyam_node_tools.py
tools/task_node_tools.py
herapheri-1.0.0.dist-info/METADATA
herapheri-1.0.0.dist-info/WHEEL
herapheri-1.0.0.dist-info/entry_points.txt
herapheri-1.0.0.dist-info/top_level.txt
herapheri-1.0.0.dist-info/RECORD
